{
  "repo": "rsbuild-plugin-react-router",
  "commit": "d62c5f24857fa871db4df0bde64813cfb5a26d72",
  "date": "2026-06-28T23:00:54.910Z",
  "node": "v22.23.0",
  "pnpm": "9.15.3",
  "platform": "linux 6.17.0-1018-azure x64",
  "profile": "large",
  "mode": "dev",
  "iterations": 3,
  "warmup": 0,
  "clean": "build",
  "logPerformance": false,
  "devRoutes": "auto",
  "devRouteTimeoutMs": 30000,
  "rspackProfile": null,
  "rspackTraceOutput": null,
  "failed": false,
  "benchmarks": [
    {
      "id": "large-355-ssr-esm",
      "routeCount": 355,
      "variant": "ssr-esm",
      "fixture": "large",
      "devRoutePathOffset": 0,
      "fixtureStats": {
        "codeModules": 10895,
        "dynamicImports": 1065,
        "routes": 355,
        "components": 6390,
        "utilities": 1420,
        "lazyModules": 1065,
        "workers": 120,
        "restrictedModules": 1187,
        "svgAssets": 1184,
        "cssModules": 217,
        "localeFiles": 111,
        "localeTotalBytes": 151289856
      },
      "devRoutePaths": [
        "/",
        "/route-0001",
        "/route-0002",
        "/route-0010",
        "/route-0050",
        "/route-0100",
        "/route-0200",
        "/route-0354"
      ],
      "cwd": ".benchmark/fixtures/large-355-ssr-esm",
      "command": "node <repo>/node_modules/@rsbuild/core/bin/rsbuild.js dev --config rsbuild.config.mjs --port <port>",
      "runs": [
        {
          "status": 0,
          "wallMs": 9244.759324,
          "readyMs": 7752.5504519999995,
          "routeTotalMs": 1442.2802580000007,
          "routeRequests": [
            {
              "path": "/",
              "status": 200,
              "ok": true,
              "ms": 1221.5191499999983,
              "bytes": 10384
            },
            {
              "path": "/route-0001",
              "status": 200,
              "ok": true,
              "ms": 30.037100999999893,
              "bytes": 10997
            },
            {
              "path": "/route-0002",
              "status": 200,
              "ok": true,
              "ms": 39.22689399999945,
              "bytes": 10847
            },
            {
              "path": "/route-0010",
              "status": 200,
              "ok": true,
              "ms": 30.67428800000016,
              "bytes": 10919
            },
            {
              "path": "/route-0050",
              "status": 200,
              "ok": true,
              "ms": 34.2548139999999,
              "bytes": 10996
            },
            {
              "path": "/route-0100",
              "status": 200,
              "ok": true,
              "ms": 27.819994999999835,
              "bytes": 10846
            },
            {
              "path": "/route-0200",
              "status": 200,
              "ok": true,
              "ms": 30.488687000000937,
              "bytes": 10992
            },
            {
              "path": "/route-0354",
              "status": 200,
              "ok": true,
              "ms": 28.080273999999918,
              "bytes": 10840
            }
          ],
          "userMs": null,
          "sysMs": null,
          "maxRssKb": null,
          "pluginReports": [],
          "rspackProfiles": [],
          "rspackTraceOutput": null
        },
        {
          "status": 0,
          "wallMs": 8749.493621999998,
          "readyMs": 7393.177095999999,
          "routeTotalMs": 1314.560089999999,
          "routeRequests": [
            {
              "path": "/",
              "status": 200,
              "ok": true,
              "ms": 1193.2168930000007,
              "bytes": 10384
            },
            {
              "path": "/route-0001",
              "status": 200,
              "ok": true,
              "ms": 17.774248999998235,
              "bytes": 10997
            },
            {
              "path": "/route-0002",
              "status": 200,
              "ok": true,
              "ms": 16.01429300000018,
              "bytes": 10847
            },
            {
              "path": "/route-0010",
              "status": 200,
              "ok": true,
              "ms": 18.829106000001048,
              "bytes": 10919
            },
            {
              "path": "/route-0050",
              "status": 200,
              "ok": true,
              "ms": 18.27019499999733,
              "bytes": 10996
            },
            {
              "path": "/route-0100",
              "status": 200,
              "ok": true,
              "ms": 17.622519999997166,
              "bytes": 10846
            },
            {
              "path": "/route-0200",
              "status": 200,
              "ok": true,
              "ms": 14.797566000001098,
              "bytes": 10992
            },
            {
              "path": "/route-0354",
              "status": 200,
              "ok": true,
              "ms": 17.932275999999547,
              "bytes": 10840
            }
          ],
          "userMs": null,
          "sysMs": null,
          "maxRssKb": null,
          "pluginReports": [],
          "rspackProfiles": [],
          "rspackTraceOutput": null
        },
        {
          "status": 0,
          "wallMs": 8782.454206000002,
          "readyMs": 7419.698789000002,
          "routeTotalMs": 1322.3087909999995,
          "routeRequests": [
            {
              "path": "/",
              "status": 200,
              "ok": true,
              "ms": 1181.690303000003,
              "bytes": 10384
            },
            {
              "path": "/route-0001",
              "status": 200,
              "ok": true,
              "ms": 20.01898500000243,
              "bytes": 10997
            },
            {
              "path": "/route-0002",
              "status": 200,
              "ok": true,
              "ms": 17.94270200000028,
              "bytes": 10847
            },
            {
              "path": "/route-0010",
              "status": 200,
              "ok": true,
              "ms": 23.04092899999887,
              "bytes": 10919
            },
            {
              "path": "/route-0050",
              "status": 200,
              "ok": true,
              "ms": 23.495867999998154,
              "bytes": 10996
            },
            {
              "path": "/route-0100",
              "status": 200,
              "ok": true,
              "ms": 17.142663000002358,
              "bytes": 10846
            },
            {
              "path": "/route-0200",
              "status": 200,
              "ok": true,
              "ms": 19.885678999999072,
              "bytes": 10992
            },
            {
              "path": "/route-0354",
              "status": 200,
              "ok": true,
              "ms": 19.018153000000893,
              "bytes": 10840
            }
          ],
          "userMs": null,
          "sysMs": null,
          "maxRssKb": null,
          "pluginReports": [],
          "rspackProfiles": [],
          "rspackTraceOutput": null
        }
      ],
      "summary": {
        "wallMs": {
          "min": 8749.493621999998,
          "median": 8782.454206000002,
          "mean": 8925.569050666667,
          "p95": 9244.759324,
          "stdev": 226.10237057191813
        },
        "readyMs": {
          "min": 7393.177095999999,
          "median": 7419.698789000002,
          "mean": 7521.808779,
          "p95": 7752.5504519999995,
          "stdev": 163.51786812460898
        },
        "routeTotalMs": {
          "min": 1314.560089999999,
          "median": 1322.3087909999995,
          "mean": 1359.7163796666664,
          "p95": 1442.2802580000007,
          "stdev": 58.46711951104411
        },
        "userMs": {
          "min": null,
          "median": null,
          "mean": null,
          "p95": null,
          "stdev": null
        },
        "sysMs": {
          "min": null,
          "median": null,
          "mean": null,
          "p95": null,
          "stdev": null
        },
        "maxRssKb": {
          "min": null,
          "median": null,
          "mean": null,
          "p95": null,
          "stdev": null
        }
      },
      "devRouteSummary": [
        {
          "path": "/",
          "count": 3,
          "statuses": [
            "200"
          ],
          "failures": 0,
          "ms": {
            "min": 1181.690303000003,
            "median": 1193.2168930000007,
            "mean": 1198.8087820000007,
            "p95": 1221.5191499999983,
            "stdev": 16.73392124355989
          },
          "bytes": {
            "min": 10384,
            "median": 10384,
            "mean": 10384,
            "p95": 10384,
            "stdev": 0
          }
        },
        {
          "path": "/route-0001",
          "count": 3,
          "statuses": [
            "200"
          ],
          "failures": 0,
          "ms": {
            "min": 17.774248999998235,
            "median": 20.01898500000243,
            "mean": 22.610111666666853,
            "p95": 30.037100999999893,
            "stdev": 5.331031035081974
          },
          "bytes": {
            "min": 10997,
            "median": 10997,
            "mean": 10997,
            "p95": 10997,
            "stdev": 0
          }
        },
        {
          "path": "/route-0002",
          "count": 3,
          "statuses": [
            "200"
          ],
          "failures": 0,
          "ms": {
            "min": 16.01429300000018,
            "median": 17.94270200000028,
            "mean": 24.394629666666635,
            "p95": 39.22689399999945,
            "stdev": 10.517500947094888
          },
          "bytes": {
            "min": 10847,
            "median": 10847,
            "mean": 10847,
            "p95": 10847,
            "stdev": 0
          }
        },
        {
          "path": "/route-0010",
          "count": 3,
          "statuses": [
            "200"
          ],
          "failures": 0,
          "ms": {
            "min": 18.829106000001048,
            "median": 23.04092899999887,
            "mean": 24.181441000000024,
            "p95": 30.67428800000016,
            "stdev": 4.902561226534945
          },
          "bytes": {
            "min": 10919,
            "median": 10919,
            "mean": 10919,
            "p95": 10919,
            "stdev": 0
          }
        },
        {
          "path": "/route-0050",
          "count": 3,
          "statuses": [
            "200"
          ],
          "failures": 0,
          "ms": {
            "min": 18.27019499999733,
            "median": 23.495867999998154,
            "mean": 25.340292333331792,
            "p95": 34.2548139999999,
            "stdev": 6.654744522261577
          },
          "bytes": {
            "min": 10996,
            "median": 10996,
            "mean": 10996,
            "p95": 10996,
            "stdev": 0
          }
        },
        {
          "path": "/route-0100",
          "count": 3,
          "statuses": [
            "200"
          ],
          "failures": 0,
          "ms": {
            "min": 17.142663000002358,
            "median": 17.622519999997166,
            "mean": 20.861725999999788,
            "p95": 27.819994999999835,
            "stdev": 4.924137575412386
          },
          "bytes": {
            "min": 10846,
            "median": 10846,
            "mean": 10846,
            "p95": 10846,
            "stdev": 0
          }
        },
        {
          "path": "/route-0200",
          "count": 3,
          "statuses": [
            "200"
          ],
          "failures": 0,
          "ms": {
            "min": 14.797566000001098,
            "median": 19.885678999999072,
            "mean": 21.723977333333703,
            "p95": 30.488687000000937,
            "stdev": 6.536427420281646
          },
          "bytes": {
            "min": 10992,
            "median": 10992,
            "mean": 10992,
            "p95": 10992,
            "stdev": 0
          }
        },
        {
          "path": "/route-0354",
          "count": 3,
          "statuses": [
            "200"
          ],
          "failures": 0,
          "ms": {
            "min": 17.932275999999547,
            "median": 19.018153000000893,
            "mean": 21.676901000000118,
            "p95": 28.080273999999918,
            "stdev": 4.549518036571039
          },
          "bytes": {
            "min": 10840,
            "median": 10840,
            "mean": 10840,
            "p95": 10840,
            "stdev": 0
          }
        }
      ],
      "pluginOperations": []
    }
  ]
}
