{
  "generatedAt": "2026-06-30T00:26:24.282Z",
  "pullRequest": "54",
  "base": {
    "ref": "main",
    "sha": "b32215908338468a1bb16320c227395513ce5c82",
    "benchmarkCommit": "b32215908338468a1bb16320c227395513ce5c82"
  },
  "head": {
    "ref": "codex/parallel-dev-compilers",
    "sha": "9519de0c217ca4964c7b11403e56bb72ec2037fd",
    "benchmarkCommit": "9519de0c217ca4964c7b11403e56bb72ec2037fd"
  },
  "runUrl": "https://github.com/rstackjs/rsbuild-plugin-react-router/actions/runs/28411597045",
  "profile": "large",
  "mode": "dev",
  "iterations": 10,
  "warmup": 0,
  "summary": {
    "baseWallMs": 9109.34154200001,
    "headWallMs": 8338.449451,
    "baseReadyMs": 9109.34154200001,
    "headReadyMs": 8338.449451,
    "baseRouteTotalMs": 1839.336513999995,
    "headRouteTotalMs": 1864.922464999996,
    "wallDeltaPercent": -8.46265438007449,
    "wallSpeedup": 1.0924502925310122,
    "readyDeltaPercent": -8.46265438007449,
    "routeTotalDeltaPercent": 1.39104241150301
  },
  "benchmarks": [
    {
      "id": "large-355-ssr-esm",
      "routeCount": 355,
      "variant": "ssr-esm",
      "baseWallMs": 9109.34154200001,
      "headWallMs": 8338.449451,
      "baseReadyMs": 9109.34154200001,
      "headReadyMs": 8338.449451,
      "baseRouteTotalMs": 1839.336513999995,
      "headRouteTotalMs": 1864.922464999996,
      "wallDeltaPercent": -8.46265438007449,
      "wallSpeedup": 1.0924502925310122,
      "baseCpuMs": null,
      "headCpuMs": null,
      "baseRssKb": null,
      "headRssKb": null
    }
  ]
}
